aem/__init__.py
aem/cnvironment_class.py
awesome_environment_manager-1.0.0.dist-info/licenses/LICENSE
awesome_environment_manager-1.0.0.dist-info/METADATA
awesome_environment_manager-1.0.0.dist-info/WHEEL
awesome_environment_manager-1.0.0.dist-info/top_level.txt
awesome_environment_manager-1.0.0.dist-info/RECORD
