Metadata-Version: 2.4
Name: awesome-environment-manager
Version: 1.0.0
Summary: A Python utility for automatically managing environment variables with type safety and easy configuration.
Author-email: Christian Heinisch <christian.heinisch@protonmail.com>
License-Expression: EUPL-1.2
Project-URL: repository, https://github.com/Cloud500/awesome-environment-manager
Requires-Python: >=3.11
License-File: LICENSE
Provides-Extra: test
Requires-Dist: pytest>=8.4.1; extra == "test"
Requires-Dist: pytest-cov>=6.2.1; extra == "test"
Requires-Dist: python-dotenv>=1.1.0; extra == "test"
Provides-Extra: build
Requires-Dist: build>=1.2.2.post1; extra == "build"
Dynamic: license-file
